[
  {
    "media": [
      
    ],
    "label_values": [
      {
        "label": "Visit time",
        "timestamp_value": 1725209210
      },
      {
        "label": "Name of application used to tag this place",
        "value": "Facebook for iPhone"
      },
      {
        "label": "Place name",
        "value": "Uzbekistan"
      }
    ],
    "fbid": "978932814276847"
  },
  {
    "media": [
      
    ],
    "label_values": [
      {
        "label": "Visit time",
        "timestamp_value": 1708070656
      },
      {
        "label": "Place name",
        "value": "Raqamli texnologiyalar vazirligi \u00e2\u0080\u0093 Ministry of Digital Technologies \u00e2\u0080\u0093 \u00d0\u009c\u00d0\u00b8\u00d0\u00bd\u00d1\u0086\u00d0\u00b8\u00d1\u0084\u00d1\u0080\u00d1\u008b"
      }
    ],
    "fbid": "849663787203751"
  },
  {
    "media": [
      
    ],
    "label_values": [
      {
        "label": "Visit time",
        "timestamp_value": 1696318142
      },
      {
        "label": "Place name",
        "value": "Axborot Va Ommaviy Kommunikatsiyalar Agentligi"
      }
    ],
    "fbid": "757946743042123"
  },
  {
    "media": [
      
    ],
    "label_values": [
      {
        "label": "Visit time",
        "timestamp_value": 1695016411
      },
      {
        "label": "Place name",
        "value": "Washington DC"
      }
    ],
    "fbid": "748038300699634"
  },
  {
    "media": [
      
    ],
    "label_values": [
      {
        "label": "Visit time",
        "timestamp_value": 1690002365
      },
      {
        "label": "Place name",
        "value": "Tashkent, Uzbekistan"
      }
    ],
    "fbid": "713719797464818"
  },
  {
    "media": [
      
    ],
    "label_values": [
      {
        "label": "Visit time",
        "timestamp_value": 1682491226
      },
      {
        "label": "Name of application used to tag this place",
        "value": "Facebook for iPhone"
      },
      {
        "label": "Place name",
        "value": "InterContinental Tashkent"
      }
    ],
    "fbid": "653991886770943"
  },
  {
    "media": [
      
    ],
    "label_values": [
      {
        "label": "Visit time",
        "timestamp_value": 1681309234
      },
      {
        "label": "Name of application used to tag this place",
        "value": "Facebook for iPhone"
      },
      {
        "label": "Place name",
        "value": "Tashkent, Uzbekistan"
      }
    ],
    "fbid": "645097304327068"
  },
  {
    "media": [
      
    ],
    "label_values": [
      {
        "label": "Visit time",
        "timestamp_value": 1677580985
      },
      {
        "label": "Name of application used to tag this place",
        "value": "Facebook for iPhone"
      },
      {
        "label": "Place name",
        "value": "Inha University in Tashkent"
      }
    ],
    "fbid": "611486401021492"
  },
  {
    "media": [
      
    ],
    "label_values": [
      {
        "label": "Visit time",
        "timestamp_value": 1677501690
      },
      {
        "label": "Name of application used to tag this place",
        "value": "Facebook for iPhone"
      },
      {
        "label": "Place name",
        "value": "Barcelona, Spain"
      }
    ],
    "fbid": "610585924444873"
  },
  {
    "media": [
      
    ],
    "label_values": [
      {
        "label": "Visit time",
        "timestamp_value": 1666589208
      },
      {
        "label": "Place name",
        "value": "Samarqand, Uzbekistan"
      }
    ],
    "fbid": "511891087647691"
  },
  {
    "media": [
      
    ],
    "label_values": [
      {
        "label": "Visit time",
        "timestamp_value": 1654233134
      },
      {
        "label": "Place name",
        "value": "Tashkent, Uzbekistan"
      }
    ],
    "fbid": "411479037688897"
  },
  {
    "media": [
      
    ],
    "label_values": [
      {
        "label": "Visit time",
        "timestamp_value": 1516863768
      },
      {
        "label": "Name of application used to tag this place",
        "value": "Facebook for Android"
      },
      {
        "label": "Place name",
        "value": "Raqamli texnologiyalar vazirligi \u00e2\u0080\u0093 Ministry of Digital Technologies \u00e2\u0080\u0093 \u00d0\u009c\u00d0\u00b8\u00d0\u00bd\u00d1\u0086\u00d0\u00b8\u00d1\u0084\u00d1\u0080\u00d1\u008b"
      }
    ],
    "fbid": "1657782130927293"
  },
  {
    "media": [
      
    ],
    "label_values": [
      {
        "label": "Visit time",
        "timestamp_value": 1511945940
      },
      {
        "label": "Place name",
        "value": "\u00d0\u00a3\u00d0\u00bd\u00d0\u00b8\u00d0\u00b2\u00d0\u00b5\u00d1\u0080\u00d1\u0081\u00d0\u00b8\u00d1\u0082\u00d0\u00b5\u00d1\u0082 \u00d0\u0098\u00d0\u00bd\u00d1\u0085\u00d0\u00b0 \u00d0\u00b2 \u00d0\u00b3. \u00d0\u00a2\u00d0\u00b0\u00d1\u0088\u00d0\u00ba\u00d0\u00b5\u00d0\u00bd\u00d1\u0082\u00d0\u00b5"
      }
    ],
    "fbid": "1602611386444368"
  },
  {
    "media": [
      
    ],
    "label_values": [
      {
        "label": "Visit time",
        "timestamp_value": 1511354091
      },
      {
        "label": "Name of application used to tag this place",
        "value": "Facebook for Android"
      },
      {
        "label": "Place name",
        "value": "O'zbekiston Milliy Teleradiokompaniyasi"
      }
    ],
    "fbid": "1595831973788976"
  },
  {
    "media": [
      
    ],
    "label_values": [
      {
        "label": "Visit time",
        "timestamp_value": 1509604689
      },
      {
        "label": "Place name",
        "value": "Raqamli texnologiyalar vazirligi \u00e2\u0080\u0093 Ministry of Digital Technologies \u00e2\u0080\u0093 \u00d0\u009c\u00d0\u00b8\u00d0\u00bd\u00d1\u0086\u00d0\u00b8\u00d1\u0084\u00d1\u0080\u00d1\u008b"
      }
    ],
    "fbid": "1576931639012343"
  },
  {
    "media": [
      
    ],
    "label_values": [
      {
        "label": "Visit time",
        "timestamp_value": 1506777651
      },
      {
        "label": "Name of application used to tag this place",
        "value": "Facebook for Android"
      },
      {
        "label": "Place name",
        "value": "Inha University in Tashkent"
      }
    ],
    "fbid": "1547455838626590"
  },
  {
    "media": [
      
    ],
    "label_values": [
      {
        "label": "Visit time",
        "timestamp_value": 1506660826
      },
      {
        "label": "Place name",
        "value": "Mirzo Ulugbek Innovation Center"
      }
    ],
    "fbid": "1546327552072752"
  },
  {
    "media": [
      
    ],
    "label_values": [
      {
        "label": "Visit time",
        "timestamp_value": 1502117892
      },
      {
        "label": "Name of application used to tag this place",
        "value": "Facebook for Android"
      },
      {
        "label": "Place name",
        "value": "\u00ed\u0095\u009c\u00ea\u00b5\u00ad\u00ea\u00b5\u00ad\u00ec\u00a0\u009c\u00ed\u0098\u0091\u00eb\u00a0\u00a5\u00eb\u008b\u00a8(Korea International Cooperation Agency)"
      }
    ],
    "fbid": "1499649883407186"
  },
  {
    "media": [
      
    ],
    "label_values": [
      {
        "label": "Visit time",
        "timestamp_value": 1496292107
      },
      {
        "label": "Place name",
        "value": "Hotel Regal Palace"
      }
    ],
    "fbid": "1433070486731793"
  },
  {
    "media": [
      
    ],
    "label_values": [
      {
        "label": "Visit time",
        "timestamp_value": 1494995479
      },
      {
        "label": "Place name",
        "value": "Zo'r Tv"
      }
    ],
    "fbid": "1418264424879066"
  },
  {
    "media": [
      
    ],
    "label_values": [
      {
        "label": "Visit time",
        "timestamp_value": 1492704666
      },
      {
        "label": "Place name",
        "value": "Amir Temur Square"
      }
    ],
    "fbid": "1391153980923444"
  },
  {
    "media": [
      
    ],
    "label_values": [
      {
        "label": "Visit time",
        "timestamp_value": 1492614217
      },
      {
        "label": "Place name",
        "value": "Minsk, Belarus"
      }
    ],
    "fbid": "1389908751047967"
  },
  {
    "media": [
      
    ],
    "label_values": [
      {
        "label": "Visit time",
        "timestamp_value": 1492445990
      },
      {
        "label": "Place name",
        "value": "Raqamli texnologiyalar vazirligi \u00e2\u0080\u0093 Ministry of Digital Technologies \u00e2\u0080\u0093 \u00d0\u009c\u00d0\u00b8\u00d0\u00bd\u00d1\u0086\u00d0\u00b8\u00d1\u0084\u00d1\u0080\u00d1\u008b"
      }
    ],
    "fbid": "1387494244622751"
  },
  {
    "media": [
      
    ],
    "label_values": [
      {
        "label": "Visit time",
        "timestamp_value": 1490341714
      },
      {
        "label": "Place name",
        "value": "\u00d0\u00a2\u00d0\u00b0\u00d1\u0088\u00d0\u00ba\u00d0\u00b5\u00d0\u00bd\u00d1\u0082\u00d1\u0081\u00d0\u00ba\u00d0\u00b8\u00d0\u00b9 \u00d1\u0083\u00d0\u00bd\u00d0\u00b8\u00d0\u00b2\u00d0\u00b5\u00d1\u0080\u00d1\u0081\u00d0\u00b8\u00d1\u0082\u00d0\u00b5\u00d1\u0082 \u00d0\u00b8\u00d0\u00bd\u00d1\u0084\u00d0\u00be\u00d1\u0080\u00d0\u00bc\u00d0\u00b0\u00d1\u0086\u00d0\u00b8\u00d0\u00be\u00d0\u00bd\u00d0\u00bd\u00d1\u008b\u00d1\u0085 \u00d1\u0082\u00d0\u00b5\u00d1\u0085\u00d0\u00bd\u00d0\u00be\u00d0\u00bb\u00d0\u00be\u00d0\u00b3\u00d0\u00b8\u00d0\u00b9"
      }
    ],
    "fbid": "1360788307293345"
  },
  {
    "media": [
      
    ],
    "label_values": [
      {
        "label": "Visit time",
        "timestamp_value": 1489572593
      },
      {
        "label": "Place name",
        "value": "Raqamli texnologiyalar vazirligi \u00e2\u0080\u0093 Ministry of Digital Technologies \u00e2\u0080\u0093 \u00d0\u009c\u00d0\u00b8\u00d0\u00bd\u00d1\u0086\u00d0\u00b8\u00d1\u0084\u00d1\u0080\u00d1\u008b"
      }
    ],
    "fbid": "1351735338198642"
  },
  {
    "media": [
      
    ],
    "label_values": [
      {
        "label": "Visit time",
        "timestamp_value": 1489212623
      },
      {
        "label": "Place name",
        "value": "Raqamli texnologiyalar vazirligi \u00e2\u0080\u0093 Ministry of Digital Technologies \u00e2\u0080\u0093 \u00d0\u009c\u00d0\u00b8\u00d0\u00bd\u00d1\u0086\u00d0\u00b8\u00d1\u0084\u00d1\u0080\u00d1\u008b"
      }
    ],
    "fbid": "1347281555310687"
  }
]